iacer/__init__.py
iacer/cli.py
iacer/config.py
iacer/exceptions.py
iacer/generate_params.py
iacer/logger.py
iacer/main.py
iacer/stack.py
iacer/termial_print.py
iacer/util.py
iacer/cli_modules/__init__.py
iacer/cli_modules/base.py
iacer/cli_modules/delete.py
iacer/cli_modules/list.py
iacer/cli_modules/test.py
iacer/plugin/__init__.py
iacer/plugin/base_plugin.py
iacer/plugin/ecs.py
iacer/plugin/error_code.py
iacer/plugin/oss.py
iacer/plugin/ros.py
iacer/plugin/vpc.py
iacer/report/__init__.py
iacer/report/generate_reports.py
iacer/report/html.css
iacer/testing/__init__.py
iacer/testing/base.py
iacer/testing/ros_stack.py
iacer-0.0.15.data/scripts/iacer
iacer-0.0.15.dist-info/LICENSE.txt
iacer-0.0.15.dist-info/METADATA
iacer-0.0.15.dist-info/WHEEL
iacer-0.0.15.dist-info/top_level.txt
iacer-0.0.15.dist-info/RECORD
